LICENSE
MANIFEST.in
README.md
setup.py
totalsum/__init__.py
totalsum/admin.py
totalsum/templates/totalsum_change_list.html
totalsum/templates/totalsum_change_list_results.html
totalsum/templatetags/__init__.py
totalsum/templatetags/totalsum.py
twentytab_totalsum_admin.egg-info/PKG-INFO
twentytab_totalsum_admin.egg-info/SOURCES.txt
twentytab_totalsum_admin.egg-info/dependency_links.txt
twentytab_totalsum_admin.egg-info/requires.txt
twentytab_totalsum_admin.egg-info/top_level.txt