Metadata-Version: 1.0
Name: twentytab-totalsum-admin
Version: 0.9
Summary: A django app that initializes admin changelist view with last row in results as sum of some numerical fields or properties
Home-page: https://github.com/20tab/twentytab-totalsum-admin
Author: 20tab S.r.l.
Author-email: info@20tab.com
License: MIT License
Platform: UNKNOWN
